.hgignore
.hgtags
CHANGES.txt
LICENSE.txt
MANIFEST.in
README.txt
bootstrap.py
buildout.cfg
setup.py
js/__init__.py
js.knockout.egg-info/PKG-INFO
js.knockout.egg-info/SOURCES.txt
js.knockout.egg-info/dependency_links.txt
js.knockout.egg-info/entry_points.txt
js.knockout.egg-info/namespace_packages.txt
js.knockout.egg-info/not-zip-safe
js.knockout.egg-info/requires.txt
js.knockout.egg-info/top_level.txt
js/knockout/__init__.py
js/knockout/test_knockout.txt
js/knockout/resources/README.txt
js/knockout/resources/knockout.js
js/knockout/resources/knockout.min.js