Metadata-Version: 1.0
Name: js.knockout
Version: 3.1.0
Summary: Fanstatic packaging of Knockout
Home-page: https://bitbucket.org/gocept/js.knockout
Author: gocept Developers
Author-email: mail@gocept.com
License: BSD
Platform: UNKNOWN
